LICENSE
README.md
setup.py
mazegroup/__init__.py
mazegroup/commands.py
mazegroup/imports.py
mazegroup/utils.py
mazegroup.egg-info/PKG-INFO
mazegroup.egg-info/SOURCES.txt
mazegroup.egg-info/dependency_links.txt
mazegroup.egg-info/entry_points.txt
mazegroup.egg-info/requires.txt
mazegroup.egg-info/top_level.txt
mazegroup/calc/__init__.py
mazegroup/cd/__init__.py
mazegroup/clear/__init__.py
mazegroup/cli/__init__.py
mazegroup/echo/__init__.py
mazegroup/help/__init__.py
mazegroup/libs/__init__.py
mazegroup/libs/fluxes.py
mazegroup/libs/termgui.py
mazegroup/libs/jygo/__init__.py
mazegroup/libs/jygo/jygo.py
mazegroup/ls/__init__.py
mazegroup/pyeval/__init__.py
mazegroup/pyexec/__init__.py
mazegroup/pypkg/__init__.py
mazegroup/quit/__init__.py
mazegroup/rud/__init__.py
mazegroup/rud/interpreter.py
mazegroup/saves/__init__.py
mazegroup/sc/__init__.py
mazegroup/sc/out/__init__.py
mazegroup/sc/temp/__init__.py
mazegroup/shell/__init__.py
mazegroup/update/__init__.py
mazegroup/version/__init__.py
mazegroup/vwft/__init__.py