Metadata-Version: 2.1
Name: mazegroup
Version: 0.1.4.3.1
Summary: MazeGroup.py is an general prupose library for Python.
Home-page: https://github.com/Geniusum/mazegroup.py
Author: Genius_um
License: UNKNOWN
Platform: UNKNOWN
Classifier: Programming Language :: Python :: 3
Classifier: License :: OSI Approved :: MIT License
Classifier: Operating System :: OS Independent
Requires-Python: >=3.9
License-File: LICENSE
